lzhfile/__init__.py
lzhfile/core.py
lzhfile/filebase.py
lzhfile/types/excel.py
lzhfile/types/ini.py
lzhfile/types/json.py
lzhfile/types/math.py
lzhfile/types/nfo.py
lzhfile/types/pdf.py
lzhfile/types/pkl.py
lzhfile/types/suffix.py
lzhfile/types/txt.py
lzhfile-1.0.0.dist-info/METADATA
lzhfile-1.0.0.dist-info/WHEEL
lzhfile-1.0.0.dist-info/top_level.txt
lzhfile-1.0.0.dist-info/RECORD
